Metadata-Version: 2.1
Name: ezdiscord
Version: 1.0.2
Summary: Made discord.py easier.
Home-page: 
Author: Karmin
License: MIT
Keywords: Made discord.py easier.
Classifier: Development Status :: 5 - Production/Stable
Classifier: Intended Audience :: Education
Classifier: Operating System :: Microsoft :: Windows :: Windows 10
Classifier: License :: OSI Approved :: MIT License
Classifier: Programming Language :: Python :: 3
Requires-Dist: os
Requires-Dist: discord.py
